AUTHORS
ChangeLog
MANIFEST.in
README.rst
requirements.txt
setup.cfg
setup.py
leonardo_newswall/__init__.py
leonardo_newswall.egg-info/PKG-INFO
leonardo_newswall.egg-info/SOURCES.txt
leonardo_newswall.egg-info/dependency_links.txt
leonardo_newswall.egg-info/not-zip-safe
leonardo_newswall.egg-info/pbr.json
leonardo_newswall.egg-info/requires.txt
leonardo_newswall.egg-info/top_level.txt
leonardo_newswall/apps/__init__.py
leonardo_newswall/apps/newswall.py
leonardo_newswall/templates/newswall/story_archive.html
leonardo_newswall/templates/newswall/story_detail.html
leonardo_newswall/templates/search/indexes/elephantblog/entry_text.txt
leonardo_newswall/templates/widget/recentnews/_item.html
leonardo_newswall/templates/widget/recentnews/default.html
leonardo_newswall/widget/__init__.py
leonardo_newswall/widget/recentnews/__init__.py
leonardo_newswall/widget/recentnews/models.py
requirements/default.txt
requirements/providers/twitter.txt